ktug_hanyang_pua
