Metadata-Version: 2.1
Name: ktug-hanyang-pua
Version: 0.1.2
Summary: KTUG Hanyang PUA table reader/writer
Home-page: https://github.com/mete0r/ktug-hanyang-pua
Author: mete0r
Author-email: mete0r@sarangbang.or.kr
License: GNU Affero General Public License v3 or later (AGPLv3+)
Keywords: KTUG,Hanyang,PUA
Platform: UNKNOWN
Classifier: Development Status :: 1 - Planning
Classifier: License :: OSI Approved :: GNU Affero General Public License v3 or later (AGPLv3+)
Classifier: Programming Language :: Python :: 2.7
Classifier: Programming Language :: Python :: 3.4
Provides-Extra: test
